COPYING
LICENSE
MANIFEST.in
README.md
cloud.conf
cloud_admin
cloud_resources.conf
cloud_scheduler
cloud_scheduler.conf
cloud_scheduler_status.conf
cloud_status
default.yaml
main.conf
setup.py
cloud_scheduler.egg-info/PKG-INFO
cloud_scheduler.egg-info/SOURCES.txt
cloud_scheduler.egg-info/dependency_links.txt
cloud_scheduler.egg-info/pbr.json
cloud_scheduler.egg-info/requires.txt
cloud_scheduler.egg-info/top_level.txt
cloudscheduler/__init__.py
cloudscheduler/__version__.py
cloudscheduler/admin_server.py
cloudscheduler/azurecluster.py
cloudscheduler/botocluster.py
cloudscheduler/cloud_init_util.py
cloudscheduler/cloud_management.py
cloudscheduler/cloudconfig.py
cloudscheduler/cluster_tools.py
cloudscheduler/config.py
cloudscheduler/configstatus.py
cloudscheduler/ec2cluster.py
cloudscheduler/googlecluster.py
cloudscheduler/info_server.py
cloudscheduler/job_containers.py
cloudscheduler/job_management.py
cloudscheduler/openstackcluster.py
cloudscheduler/proxy_refreshers.py
cloudscheduler/stratuslabcluster.py
cloudscheduler/utilities.py
cloudscheduler/vm_containers.py
cloudscheduler/wsdl/README
cloudscheduler/wsdl/condorCgahp.wsdl
cloudscheduler/wsdl/condorCollector.wsdl
cloudscheduler/wsdl/condorCredd.wsdl
cloudscheduler/wsdl/condorDagman.wsdl
cloudscheduler/wsdl/condorDbmsd.wsdl
cloudscheduler/wsdl/condorDcskel.wsdl
cloudscheduler/wsdl/condorEventd.wsdl
cloudscheduler/wsdl/condorGridmanager.wsdl
cloudscheduler/wsdl/condorHad.wsdl
cloudscheduler/wsdl/condorJobRouter.wsdl
cloudscheduler/wsdl/condorKbdd.wsdl
cloudscheduler/wsdl/condorLeaseManager.wsdl
cloudscheduler/wsdl/condorMaster.wsdl
cloudscheduler/wsdl/condorNegotiator.wsdl
cloudscheduler/wsdl/condorSchedd.wsdl
cloudscheduler/wsdl/condorShadow.wsdl
cloudscheduler/wsdl/condorStartd.wsdl
cloudscheduler/wsdl/condorStartdFactory.wsdl
cloudscheduler/wsdl/condorStarter.wsdl
cloudscheduler/wsdl/condorTransferd.wsdl
cloudscheduler/wsdl/condorTt.wsdl
cloudscheduler/wsdl/condorVMgahp.wsdl
scripts/cloud_scheduler
scripts/cloud_scheduler.init.d
scripts/cloud_scheduler.sysconf
scripts/condor_consistency.sh
scripts/csmonitor
scripts/csquota.py
scripts/rc2cs.py
scripts/rest_client_test.sh
scripts/condor/manager/README
