Metadata-Version: 1.0
Name: cloud-scheduler
Version: 1.13.2
Summary: A cloud-enabled distributed resource manager
Home-page: http://github.com/hep-gc/cloud-scheduler
Author: Duncan Penfold-Brown, Chris Usher, Patrick Armstrong, Ian Gable, Michael Paterson, Andre Charbonneau
Author-email: mhp@uvic.ca
License: 'GPL3' or 'Apache 2'
Platform: UNKNOWN
